chatgpt_command.py
chatgpt_command-0.1.0.dist-info/LICENSE
chatgpt_command-0.1.0.dist-info/METADATA
chatgpt_command-0.1.0.dist-info/WHEEL
chatgpt_command-0.1.0.dist-info/entry_points.txt
chatgpt_command-0.1.0.dist-info/RECORD
