Metadata-Version: 2.1
Name: chatgpt-command
Version: 0.1.0
Summary: 
Author: Juan Gonzalez
Author-email: jrg2156@gmail.com
Requires-Python: >=3.11,<4.0
Classifier: Programming Language :: Python :: 3
Classifier: Programming Language :: Python :: 3.11
Classifier: Programming Language :: Python :: 3.12
Requires-Dist: openai (>=1.10.0,<2.0.0)
Requires-Dist: psutil (>=5.9.8,<6.0.0)
Requires-Dist: tiktoken (>=0.5.2,<0.6.0)
